{
  "instances": [
    {
      "id": "1_kloppenheim_02_enamel",
      "name": "Kloppenheim 02 Enamel",
      "category": "art",
      "categoryFolder": "3D_models",
      "material": "enamel",
      "model": "3D_models.blend_geometry_0.002",
      "environment": "kloppenheim_02_4k.exr",
      "preview": "/instances/3D_models/1_kloppenheim_02_enamel/train/frame_00011.png",
      "images": {
        "rgb": [
          "frame_00001.png",
          "frame_00002.png",
          "frame_00003.png",
          "frame_00004.png",
          "frame_00005.png",
          "frame_00006.png",
          "frame_00007.png",
          "frame_00008.png",
          "frame_00009.png",
          "frame_00010.png",
          "frame_00011.png",
          "frame_00012.png",
          "frame_00013.png",
          "frame_00014.png",
          "frame_00015.png",
          "frame_00016.png",
          "frame_00017.png",
          "frame_00018.png",
          "frame_00019.png",
          "frame_00020.png",
          "frame_00021.png",
          "frame_00022.png",
          "frame_00023.png",
          "frame_00024.png",
          "frame_00025.png",
          "frame_00026.png",
          "frame_00027.png",
          "frame_00028.png",
          "frame_00029.png",
          "frame_00030.png",
          "frame_00031.png",
          "frame_00032.png",
          "frame_00033.png",
          "frame_00034.png",
          "frame_00035.png",
          "frame_00036.png",
          "frame_00037.png",
          "frame_00038.png",
          "frame_00039.png",
          "frame_00040.png",
          "frame_00041.png",
          "frame_00042.png",
          "frame_00043.png",
          "frame_00044.png",
          "frame_00045.png",
          "frame_00046.png",
          "frame_00047.png",
          "frame_00048.png",
          "frame_00049.png",
          "frame_00050.png"
        ],
        "depth": [
          "frame_00001.png",
          "frame_00002.png",
          "frame_00003.png",
          "frame_00004.png",
          "frame_00005.png",
          "frame_00006.png",
          "frame_00007.png",
          "frame_00008.png",
          "frame_00009.png",
          "frame_00010.png",
          "frame_00011.png",
          "frame_00012.png",
          "frame_00013.png",
          "frame_00014.png",
          "frame_00015.png",
          "frame_00016.png",
          "frame_00017.png",
          "frame_00018.png",
          "frame_00019.png",
          "frame_00020.png",
          "frame_00021.png",
          "frame_00022.png",
          "frame_00023.png",
          "frame_00024.png",
          "frame_00025.png",
          "frame_00026.png",
          "frame_00027.png",
          "frame_00028.png",
          "frame_00029.png",
          "frame_00030.png",
          "frame_00031.png",
          "frame_00032.png",
          "frame_00033.png",
          "frame_00034.png",
          "frame_00035.png",
          "frame_00036.png",
          "frame_00037.png",
          "frame_00038.png",
          "frame_00039.png",
          "frame_00040.png",
          "frame_00041.png",
          "frame_00042.png",
          "frame_00043.png",
          "frame_00044.png",
          "frame_00045.png",
          "frame_00046.png",
          "frame_00047.png",
          "frame_00048.png",
          "frame_00049.png",
          "frame_00050.png"
        ],
        "normal": [
          "frame_00001.png",
          "frame_00002.png",
          "frame_00003.png",
          "frame_00004.png",
          "frame_00005.png",
          "frame_00006.png",
          "frame_00007.png",
          "frame_00008.png",
          "frame_00009.png",
          "frame_00010.png",
          "frame_00011.png",
          "frame_00012.png",
          "frame_00013.png",
          "frame_00014.png",
          "frame_00015.png",
          "frame_00016.png",
          "frame_00017.png",
          "frame_00018.png",
          "frame_00019.png",
          "frame_00020.png",
          "frame_00021.png",
          "frame_00022.png",
          "frame_00023.png",
          "frame_00024.png",
          "frame_00025.png",
          "frame_00026.png",
          "frame_00027.png",
          "frame_00028.png",
          "frame_00029.png",
          "frame_00030.png",
          "frame_00031.png",
          "frame_00032.png",
          "frame_00033.png",
          "frame_00034.png",
          "frame_00035.png",
          "frame_00036.png",
          "frame_00037.png",
          "frame_00038.png",
          "frame_00039.png",
          "frame_00040.png",
          "frame_00041.png",
          "frame_00042.png",
          "frame_00043.png",
          "frame_00044.png",
          "frame_00045.png",
          "frame_00046.png",
          "frame_00047.png",
          "frame_00048.png",
          "frame_00049.png",
          "frame_00050.png"
        ],
        "mask": [
          "frame_00001.png",
          "frame_00002.png",
          "frame_00003.png",
          "frame_00004.png",
          "frame_00005.png",
          "frame_00006.png",
          "frame_00007.png",
          "frame_00008.png",
          "frame_00009.png",
          "frame_00010.png",
          "frame_00011.png",
          "frame_00012.png",
          "frame_00013.png",
          "frame_00014.png",
          "frame_00015.png",
          "frame_00016.png",
          "frame_00017.png",
          "frame_00018.png",
          "frame_00019.png",
          "frame_00020.png",
          "frame_00021.png",
          "frame_00022.png",
          "frame_00023.png",
          "frame_00024.png",
          "frame_00025.png",
          "frame_00026.png",
          "frame_00027.png",
          "frame_00028.png",
          "frame_00029.png",
          "frame_00030.png",
          "frame_00031.png",
          "frame_00032.png",
          "frame_00033.png",
          "frame_00034.png",
          "frame_00035.png",
          "frame_00036.png",
          "frame_00037.png",
          "frame_00038.png",
          "frame_00039.png",
          "frame_00040.png",
          "frame_00041.png",
          "frame_00042.png",
          "frame_00043.png",
          "frame_00044.png",
          "frame_00045.png",
          "frame_00046.png",
          "frame_00047.png",
          "frame_00048.png",
          "frame_00049.png",
          "frame_00050.png"
        ]
      },
      "frameCount": 50,
      "metadata": {
        "hasGlass": false,
        "isGenerated": true,
        "transparent": false
      }
    },
    {
      "id": "2_kloppenheim_02_enamel",
      "name": "Kloppenheim 02 Enamel",
      "category": "art",
      "categoryFolder": "3D_models",
      "material": "enamel",
      "model": "3D_models.blend_geometry_0.001",
      "environment": "kloppenheim_02_4k.exr",
      "preview": "/instances/3D_models/2_kloppenheim_02_enamel/train/frame_00011.png",
      "images": {
        "rgb": [
          "frame_00001.png",
          "frame_00002.png",
          "frame_00003.png",
          "frame_00004.png",
          "frame_00005.png",
          "frame_00006.png",
          "frame_00007.png",
          "frame_00008.png",
          "frame_00009.png",
          "frame_00010.png",
          "frame_00011.png",
          "frame_00012.png",
          "frame_00013.png",
          "frame_00014.png",
          "frame_00015.png",
          "frame_00016.png",
          "frame_00017.png",
          "frame_00018.png",
          "frame_00019.png",
          "frame_00020.png",
          "frame_00021.png",
          "frame_00022.png",
          "frame_00023.png",
          "frame_00024.png",
          "frame_00025.png",
          "frame_00026.png",
          "frame_00027.png",
          "frame_00028.png",
          "frame_00029.png",
          "frame_00030.png",
          "frame_00031.png",
          "frame_00032.png",
          "frame_00033.png",
          "frame_00034.png",
          "frame_00035.png",
          "frame_00036.png",
          "frame_00037.png",
          "frame_00038.png",
          "frame_00039.png",
          "frame_00040.png",
          "frame_00041.png",
          "frame_00042.png",
          "frame_00043.png",
          "frame_00044.png",
          "frame_00045.png",
          "frame_00046.png",
          "frame_00047.png",
          "frame_00048.png",
          "frame_00049.png",
          "frame_00050.png"
        ],
        "depth": [
          "frame_00001.png",
          "frame_00002.png",
          "frame_00003.png",
          "frame_00004.png",
          "frame_00005.png",
          "frame_00006.png",
          "frame_00007.png",
          "frame_00008.png",
          "frame_00009.png",
          "frame_00010.png",
          "frame_00011.png",
          "frame_00012.png",
          "frame_00013.png",
          "frame_00014.png",
          "frame_00015.png",
          "frame_00016.png",
          "frame_00017.png",
          "frame_00018.png",
          "frame_00019.png",
          "frame_00020.png",
          "frame_00021.png",
          "frame_00022.png",
          "frame_00023.png",
          "frame_00024.png",
          "frame_00025.png",
          "frame_00026.png",
          "frame_00027.png",
          "frame_00028.png",
          "frame_00029.png",
          "frame_00030.png",
          "frame_00031.png",
          "frame_00032.png",
          "frame_00033.png",
          "frame_00034.png",
          "frame_00035.png",
          "frame_00036.png",
          "frame_00037.png",
          "frame_00038.png",
          "frame_00039.png",
          "frame_00040.png",
          "frame_00041.png",
          "frame_00042.png",
          "frame_00043.png",
          "frame_00044.png",
          "frame_00045.png",
          "frame_00046.png",
          "frame_00047.png",
          "frame_00048.png",
          "frame_00049.png",
          "frame_00050.png"
        ],
        "normal": [
          "frame_00001.png",
          "frame_00002.png",
          "frame_00003.png",
          "frame_00004.png",
          "frame_00005.png",
          "frame_00006.png",
          "frame_00007.png",
          "frame_00008.png",
          "frame_00009.png",
          "frame_00010.png",
          "frame_00011.png",
          "frame_00012.png",
          "frame_00013.png",
          "frame_00014.png",
          "frame_00015.png",
          "frame_00016.png",
          "frame_00017.png",
          "frame_00018.png",
          "frame_00019.png",
          "frame_00020.png",
          "frame_00021.png",
          "frame_00022.png",
          "frame_00023.png",
          "frame_00024.png",
          "frame_00025.png",
          "frame_00026.png",
          "frame_00027.png",
          "frame_00028.png",
          "frame_00029.png",
          "frame_00030.png",
          "frame_00031.png",
          "frame_00032.png",
          "frame_00033.png",
          "frame_00034.png",
          "frame_00035.png",
          "frame_00036.png",
          "frame_00037.png",
          "frame_00038.png",
          "frame_00039.png",
          "frame_00040.png",
          "frame_00041.png",
          "frame_00042.png",
          "frame_00043.png",
          "frame_00044.png",
          "frame_00045.png",
          "frame_00046.png",
          "frame_00047.png",
          "frame_00048.png",
          "frame_00049.png",
          "frame_00050.png"
        ],
        "mask": [
          "frame_00001.png",
          "frame_00002.png",
          "frame_00003.png",
          "frame_00004.png",
          "frame_00005.png",
          "frame_00006.png",
          "frame_00007.png",
          "frame_00008.png",
          "frame_00009.png",
          "frame_00010.png",
          "frame_00011.png",
          "frame_00012.png",
          "frame_00013.png",
          "frame_00014.png",
          "frame_00015.png",
          "frame_00016.png",
          "frame_00017.png",
          "frame_00018.png",
          "frame_00019.png",
          "frame_00020.png",
          "frame_00021.png",
          "frame_00022.png",
          "frame_00023.png",
          "frame_00024.png",
          "frame_00025.png",
          "frame_00026.png",
          "frame_00027.png",
          "frame_00028.png",
          "frame_00029.png",
          "frame_00030.png",
          "frame_00031.png",
          "frame_00032.png",
          "frame_00033.png",
          "frame_00034.png",
          "frame_00035.png",
          "frame_00036.png",
          "frame_00037.png",
          "frame_00038.png",
          "frame_00039.png",
          "frame_00040.png",
          "frame_00041.png",
          "frame_00042.png",
          "frame_00043.png",
          "frame_00044.png",
          "frame_00045.png",
          "frame_00046.png",
          "frame_00047.png",
          "frame_00048.png",
          "frame_00049.png",
          "frame_00050.png"
        ]
      },
      "frameCount": 50,
      "metadata": {
        "hasGlass": false,
        "isGenerated": true,
        "transparent": false
      }
    },
    {
      "id": "3_kloppenheim_02_enamel",
      "name": "Kloppenheim 02 Enamel",
      "category": "art",
      "categoryFolder": "3D_models",
      "material": "enamel",
      "model": "3D_models.blend_geometry_0",
      "environment": "kloppenheim_02_4k.exr",
      "preview": "/instances/3D_models/3_kloppenheim_02_enamel/train/frame_00011.png",
      "images": {
        "rgb": [
          "frame_00001.png",
          "frame_00002.png",
          "frame_00003.png",
          "frame_00004.png",
          "frame_00005.png",
          "frame_00006.png",
          "frame_00007.png",
          "frame_00008.png",
          "frame_00009.png",
          "frame_00010.png",
          "frame_00011.png",
          "frame_00012.png",
          "frame_00013.png",
          "frame_00014.png",
          "frame_00015.png",
          "frame_00016.png",
          "frame_00017.png",
          "frame_00018.png",
          "frame_00019.png",
          "frame_00020.png",
          "frame_00021.png",
          "frame_00022.png",
          "frame_00023.png",
          "frame_00024.png",
          "frame_00025.png",
          "frame_00026.png",
          "frame_00027.png",
          "frame_00028.png",
          "frame_00029.png",
          "frame_00030.png",
          "frame_00031.png",
          "frame_00032.png",
          "frame_00033.png",
          "frame_00034.png",
          "frame_00035.png",
          "frame_00036.png",
          "frame_00037.png",
          "frame_00038.png",
          "frame_00039.png",
          "frame_00040.png",
          "frame_00041.png",
          "frame_00042.png",
          "frame_00043.png",
          "frame_00044.png",
          "frame_00045.png",
          "frame_00046.png",
          "frame_00047.png",
          "frame_00048.png",
          "frame_00049.png",
          "frame_00050.png"
        ],
        "depth": [
          "frame_00001.png",
          "frame_00002.png",
          "frame_00003.png",
          "frame_00004.png",
          "frame_00005.png",
          "frame_00006.png",
          "frame_00007.png",
          "frame_00008.png",
          "frame_00009.png",
          "frame_00010.png",
          "frame_00011.png",
          "frame_00012.png",
          "frame_00013.png",
          "frame_00014.png",
          "frame_00015.png",
          "frame_00016.png",
          "frame_00017.png",
          "frame_00018.png",
          "frame_00019.png",
          "frame_00020.png",
          "frame_00021.png",
          "frame_00022.png",
          "frame_00023.png",
          "frame_00024.png",
          "frame_00025.png",
          "frame_00026.png",
          "frame_00027.png",
          "frame_00028.png",
          "frame_00029.png",
          "frame_00030.png",
          "frame_00031.png",
          "frame_00032.png",
          "frame_00033.png",
          "frame_00034.png",
          "frame_00035.png",
          "frame_00036.png",
          "frame_00037.png",
          "frame_00038.png",
          "frame_00039.png",
          "frame_00040.png",
          "frame_00041.png",
          "frame_00042.png",
          "frame_00043.png",
          "frame_00044.png",
          "frame_00045.png",
          "frame_00046.png",
          "frame_00047.png",
          "frame_00048.png",
          "frame_00049.png",
          "frame_00050.png"
        ],
        "normal": [
          "frame_00001.png",
          "frame_00002.png",
          "frame_00003.png",
          "frame_00004.png",
          "frame_00005.png",
          "frame_00006.png",
          "frame_00007.png",
          "frame_00008.png",
          "frame_00009.png",
          "frame_00010.png",
          "frame_00011.png",
          "frame_00012.png",
          "frame_00013.png",
          "frame_00014.png",
          "frame_00015.png",
          "frame_00016.png",
          "frame_00017.png",
          "frame_00018.png",
          "frame_00019.png",
          "frame_00020.png",
          "frame_00021.png",
          "frame_00022.png",
          "frame_00023.png",
          "frame_00024.png",
          "frame_00025.png",
          "frame_00026.png",
          "frame_00027.png",
          "frame_00028.png",
          "frame_00029.png",
          "frame_00030.png",
          "frame_00031.png",
          "frame_00032.png",
          "frame_00033.png",
          "frame_00034.png",
          "frame_00035.png",
          "frame_00036.png",
          "frame_00037.png",
          "frame_00038.png",
          "frame_00039.png",
          "frame_00040.png",
          "frame_00041.png",
          "frame_00042.png",
          "frame_00043.png",
          "frame_00044.png",
          "frame_00045.png",
          "frame_00046.png",
          "frame_00047.png",
          "frame_00048.png",
          "frame_00049.png",
          "frame_00050.png"
        ],
        "mask": [
          "frame_00001.png",
          "frame_00002.png",
          "frame_00003.png",
          "frame_00004.png",
          "frame_00005.png",
          "frame_00006.png",
          "frame_00007.png",
          "frame_00008.png",
          "frame_00009.png",
          "frame_00010.png",
          "frame_00011.png",
          "frame_00012.png",
          "frame_00013.png",
          "frame_00014.png",
          "frame_00015.png",
          "frame_00016.png",
          "frame_00017.png",
          "frame_00018.png",
          "frame_00019.png",
          "frame_00020.png",
          "frame_00021.png",
          "frame_00022.png",
          "frame_00023.png",
          "frame_00024.png",
          "frame_00025.png",
          "frame_00026.png",
          "frame_00027.png",
          "frame_00028.png",
          "frame_00029.png",
          "frame_00030.png",
          "frame_00031.png",
          "frame_00032.png",
          "frame_00033.png",
          "frame_00034.png",
          "frame_00035.png",
          "frame_00036.png",
          "frame_00037.png",
          "frame_00038.png",
          "frame_00039.png",
          "frame_00040.png",
          "frame_00041.png",
          "frame_00042.png",
          "frame_00043.png",
          "frame_00044.png",
          "frame_00045.png",
          "frame_00046.png",
          "frame_00047.png",
          "frame_00048.png",
          "frame_00049.png",
          "frame_00050.png"
        ]
      },
      "frameCount": 50,
      "metadata": {
        "hasGlass": false,
        "isGenerated": true,
        "transparent": false
      }
    },
    {
      "id": "1_kloppenheim_02_enamel_glass",
      "name": "Kloppenheim 02 Enamel Glass",
      "category": "art",
      "categoryFolder": "3D_models_glass",
      "material": "enamel",
      "model": "3D_models.blend_geometry_0.002",
      "environment": "kloppenheim_02_4k.exr",
      "preview": "/instances/3D_models_glass/1_kloppenheim_02_enamel_glass/train/frame_00011.png",
      "images": {
        "rgb": [
          "frame_00001.png",
          "frame_00002.png",
          "frame_00003.png",
          "frame_00004.png",
          "frame_00005.png",
          "frame_00006.png",
          "frame_00007.png",
          "frame_00008.png",
          "frame_00009.png",
          "frame_00010.png",
          "frame_00011.png",
          "frame_00012.png",
          "frame_00013.png",
          "frame_00014.png",
          "frame_00015.png",
          "frame_00016.png",
          "frame_00017.png",
          "frame_00018.png",
          "frame_00019.png",
          "frame_00020.png",
          "frame_00021.png",
          "frame_00022.png",
          "frame_00023.png",
          "frame_00024.png",
          "frame_00025.png",
          "frame_00026.png",
          "frame_00027.png",
          "frame_00028.png",
          "frame_00029.png",
          "frame_00030.png",
          "frame_00031.png",
          "frame_00032.png",
          "frame_00033.png",
          "frame_00034.png",
          "frame_00035.png",
          "frame_00036.png",
          "frame_00037.png",
          "frame_00038.png",
          "frame_00039.png",
          "frame_00040.png",
          "frame_00041.png",
          "frame_00042.png",
          "frame_00043.png",
          "frame_00044.png",
          "frame_00045.png",
          "frame_00046.png",
          "frame_00047.png",
          "frame_00048.png",
          "frame_00049.png",
          "frame_00050.png"
        ],
        "depth": [
          "frame_00001.png",
          "frame_00002.png",
          "frame_00003.png",
          "frame_00004.png",
          "frame_00005.png",
          "frame_00006.png",
          "frame_00007.png",
          "frame_00008.png",
          "frame_00009.png",
          "frame_00010.png",
          "frame_00011.png",
          "frame_00012.png",
          "frame_00013.png",
          "frame_00014.png",
          "frame_00015.png",
          "frame_00016.png",
          "frame_00017.png",
          "frame_00018.png",
          "frame_00019.png",
          "frame_00020.png",
          "frame_00021.png",
          "frame_00022.png",
          "frame_00023.png",
          "frame_00024.png",
          "frame_00025.png",
          "frame_00026.png",
          "frame_00027.png",
          "frame_00028.png",
          "frame_00029.png",
          "frame_00030.png",
          "frame_00031.png",
          "frame_00032.png",
          "frame_00033.png",
          "frame_00034.png",
          "frame_00035.png",
          "frame_00036.png",
          "frame_00037.png",
          "frame_00038.png",
          "frame_00039.png",
          "frame_00040.png",
          "frame_00041.png",
          "frame_00042.png",
          "frame_00043.png",
          "frame_00044.png",
          "frame_00045.png",
          "frame_00046.png",
          "frame_00047.png",
          "frame_00048.png",
          "frame_00049.png",
          "frame_00050.png"
        ],
        "normal": [
          "frame_00001.png",
          "frame_00002.png",
          "frame_00003.png",
          "frame_00004.png",
          "frame_00005.png",
          "frame_00006.png",
          "frame_00007.png",
          "frame_00008.png",
          "frame_00009.png",
          "frame_00010.png",
          "frame_00011.png",
          "frame_00012.png",
          "frame_00013.png",
          "frame_00014.png",
          "frame_00015.png",
          "frame_00016.png",
          "frame_00017.png",
          "frame_00018.png",
          "frame_00019.png",
          "frame_00020.png",
          "frame_00021.png",
          "frame_00022.png",
          "frame_00023.png",
          "frame_00024.png",
          "frame_00025.png",
          "frame_00026.png",
          "frame_00027.png",
          "frame_00028.png",
          "frame_00029.png",
          "frame_00030.png",
          "frame_00031.png",
          "frame_00032.png",
          "frame_00033.png",
          "frame_00034.png",
          "frame_00035.png",
          "frame_00036.png",
          "frame_00037.png",
          "frame_00038.png",
          "frame_00039.png",
          "frame_00040.png",
          "frame_00041.png",
          "frame_00042.png",
          "frame_00043.png",
          "frame_00044.png",
          "frame_00045.png",
          "frame_00046.png",
          "frame_00047.png",
          "frame_00048.png",
          "frame_00049.png",
          "frame_00050.png"
        ],
        "mask": [
          "frame_00001.png",
          "frame_00002.png",
          "frame_00003.png",
          "frame_00004.png",
          "frame_00005.png",
          "frame_00006.png",
          "frame_00007.png",
          "frame_00008.png",
          "frame_00009.png",
          "frame_00010.png",
          "frame_00011.png",
          "frame_00012.png",
          "frame_00013.png",
          "frame_00014.png",
          "frame_00015.png",
          "frame_00016.png",
          "frame_00017.png",
          "frame_00018.png",
          "frame_00019.png",
          "frame_00020.png",
          "frame_00021.png",
          "frame_00022.png",
          "frame_00023.png",
          "frame_00024.png",
          "frame_00025.png",
          "frame_00026.png",
          "frame_00027.png",
          "frame_00028.png",
          "frame_00029.png",
          "frame_00030.png",
          "frame_00031.png",
          "frame_00032.png",
          "frame_00033.png",
          "frame_00034.png",
          "frame_00035.png",
          "frame_00036.png",
          "frame_00037.png",
          "frame_00038.png",
          "frame_00039.png",
          "frame_00040.png",
          "frame_00041.png",
          "frame_00042.png",
          "frame_00043.png",
          "frame_00044.png",
          "frame_00045.png",
          "frame_00046.png",
          "frame_00047.png",
          "frame_00048.png",
          "frame_00049.png",
          "frame_00050.png"
        ]
      },
      "frameCount": 50,
      "metadata": {
        "hasGlass": true,
        "isGenerated": true,
        "transparent": false
      }
    },
    {
      "id": "2_kloppenheim_02_enamel_glass",
      "name": "Kloppenheim 02 Enamel Glass",
      "category": "art",
      "categoryFolder": "3D_models_glass",
      "material": "enamel",
      "model": "3D_models.blend_geometry_0.001",
      "environment": "kloppenheim_02_4k.exr",
      "preview": "/instances/3D_models_glass/2_kloppenheim_02_enamel_glass/train/frame_00011.png",
      "images": {
        "rgb": [
          "frame_00001.png",
          "frame_00002.png",
          "frame_00003.png",
          "frame_00004.png",
          "frame_00005.png",
          "frame_00006.png",
          "frame_00007.png",
          "frame_00008.png",
          "frame_00009.png",
          "frame_00010.png",
          "frame_00011.png",
          "frame_00012.png",
          "frame_00013.png",
          "frame_00014.png",
          "frame_00015.png",
          "frame_00016.png",
          "frame_00017.png",
          "frame_00018.png",
          "frame_00019.png",
          "frame_00020.png",
          "frame_00021.png",
          "frame_00022.png",
          "frame_00023.png",
          "frame_00024.png",
          "frame_00025.png",
          "frame_00026.png",
          "frame_00027.png",
          "frame_00028.png",
          "frame_00029.png",
          "frame_00030.png",
          "frame_00031.png",
          "frame_00032.png",
          "frame_00033.png",
          "frame_00034.png",
          "frame_00035.png",
          "frame_00036.png",
          "frame_00037.png",
          "frame_00038.png",
          "frame_00039.png",
          "frame_00040.png",
          "frame_00041.png",
          "frame_00042.png",
          "frame_00043.png",
          "frame_00044.png",
          "frame_00045.png",
          "frame_00046.png",
          "frame_00047.png",
          "frame_00048.png",
          "frame_00049.png",
          "frame_00050.png"
        ],
        "depth": [
          "frame_00001.png",
          "frame_00002.png",
          "frame_00003.png",
          "frame_00004.png",
          "frame_00005.png",
          "frame_00006.png",
          "frame_00007.png",
          "frame_00008.png",
          "frame_00009.png",
          "frame_00010.png",
          "frame_00011.png",
          "frame_00012.png",
          "frame_00013.png",
          "frame_00014.png",
          "frame_00015.png",
          "frame_00016.png",
          "frame_00017.png",
          "frame_00018.png",
          "frame_00019.png",
          "frame_00020.png",
          "frame_00021.png",
          "frame_00022.png",
          "frame_00023.png",
          "frame_00024.png",
          "frame_00025.png",
          "frame_00026.png",
          "frame_00027.png",
          "frame_00028.png",
          "frame_00029.png",
          "frame_00030.png",
          "frame_00031.png",
          "frame_00032.png",
          "frame_00033.png",
          "frame_00034.png",
          "frame_00035.png",
          "frame_00036.png",
          "frame_00037.png",
          "frame_00038.png",
          "frame_00039.png",
          "frame_00040.png",
          "frame_00041.png",
          "frame_00042.png",
          "frame_00043.png",
          "frame_00044.png",
          "frame_00045.png",
          "frame_00046.png",
          "frame_00047.png",
          "frame_00048.png",
          "frame_00049.png",
          "frame_00050.png"
        ],
        "normal": [
          "frame_00001.png",
          "frame_00002.png",
          "frame_00003.png",
          "frame_00004.png",
          "frame_00005.png",
          "frame_00006.png",
          "frame_00007.png",
          "frame_00008.png",
          "frame_00009.png",
          "frame_00010.png",
          "frame_00011.png",
          "frame_00012.png",
          "frame_00013.png",
          "frame_00014.png",
          "frame_00015.png",
          "frame_00016.png",
          "frame_00017.png",
          "frame_00018.png",
          "frame_00019.png",
          "frame_00020.png",
          "frame_00021.png",
          "frame_00022.png",
          "frame_00023.png",
          "frame_00024.png",
          "frame_00025.png",
          "frame_00026.png",
          "frame_00027.png",
          "frame_00028.png",
          "frame_00029.png",
          "frame_00030.png",
          "frame_00031.png",
          "frame_00032.png",
          "frame_00033.png",
          "frame_00034.png",
          "frame_00035.png",
          "frame_00036.png",
          "frame_00037.png",
          "frame_00038.png",
          "frame_00039.png",
          "frame_00040.png",
          "frame_00041.png",
          "frame_00042.png",
          "frame_00043.png",
          "frame_00044.png",
          "frame_00045.png",
          "frame_00046.png",
          "frame_00047.png",
          "frame_00048.png",
          "frame_00049.png",
          "frame_00050.png"
        ],
        "mask": [
          "frame_00001.png",
          "frame_00002.png",
          "frame_00003.png",
          "frame_00004.png",
          "frame_00005.png",
          "frame_00006.png",
          "frame_00007.png",
          "frame_00008.png",
          "frame_00009.png",
          "frame_00010.png",
          "frame_00011.png",
          "frame_00012.png",
          "frame_00013.png",
          "frame_00014.png",
          "frame_00015.png",
          "frame_00016.png",
          "frame_00017.png",
          "frame_00018.png",
          "frame_00019.png",
          "frame_00020.png",
          "frame_00021.png",
          "frame_00022.png",
          "frame_00023.png",
          "frame_00024.png",
          "frame_00025.png",
          "frame_00026.png",
          "frame_00027.png",
          "frame_00028.png",
          "frame_00029.png",
          "frame_00030.png",
          "frame_00031.png",
          "frame_00032.png",
          "frame_00033.png",
          "frame_00034.png",
          "frame_00035.png",
          "frame_00036.png",
          "frame_00037.png",
          "frame_00038.png",
          "frame_00039.png",
          "frame_00040.png",
          "frame_00041.png",
          "frame_00042.png",
          "frame_00043.png",
          "frame_00044.png",
          "frame_00045.png",
          "frame_00046.png",
          "frame_00047.png",
          "frame_00048.png",
          "frame_00049.png",
          "frame_00050.png"
        ]
      },
      "frameCount": 50,
      "metadata": {
        "hasGlass": true,
        "isGenerated": true,
        "transparent": false
      }
    },
    {
      "id": "3_kloppenheim_02_enamel_glass",
      "name": "Kloppenheim 02 Enamel Glass",
      "category": "art",
      "categoryFolder": "3D_models_glass",
      "material": "enamel",
      "model": "3D_models.blend_geometry_0",
      "environment": "kloppenheim_02_4k.exr",
      "preview": "/instances/3D_models_glass/3_kloppenheim_02_enamel_glass/train/frame_00011.png",
      "images": {
        "rgb": [
          "frame_00001.png",
          "frame_00002.png",
          "frame_00003.png",
          "frame_00004.png",
          "frame_00005.png",
          "frame_00006.png",
          "frame_00007.png",
          "frame_00008.png",
          "frame_00009.png",
          "frame_00010.png",
          "frame_00011.png",
          "frame_00012.png",
          "frame_00013.png",
          "frame_00014.png",
          "frame_00015.png",
          "frame_00016.png",
          "frame_00017.png",
          "frame_00018.png",
          "frame_00019.png",
          "frame_00020.png",
          "frame_00021.png",
          "frame_00022.png",
          "frame_00023.png",
          "frame_00024.png",
          "frame_00025.png",
          "frame_00026.png",
          "frame_00027.png",
          "frame_00028.png",
          "frame_00029.png",
          "frame_00030.png",
          "frame_00031.png",
          "frame_00032.png",
          "frame_00033.png",
          "frame_00034.png",
          "frame_00035.png",
          "frame_00036.png",
          "frame_00037.png",
          "frame_00038.png",
          "frame_00039.png",
          "frame_00040.png",
          "frame_00041.png",
          "frame_00042.png",
          "frame_00043.png",
          "frame_00044.png",
          "frame_00045.png",
          "frame_00046.png",
          "frame_00047.png",
          "frame_00048.png",
          "frame_00049.png",
          "frame_00050.png"
        ],
        "depth": [
          "frame_00001.png",
          "frame_00002.png",
          "frame_00003.png",
          "frame_00004.png",
          "frame_00005.png",
          "frame_00006.png",
          "frame_00007.png",
          "frame_00008.png",
          "frame_00009.png",
          "frame_00010.png",
          "frame_00011.png",
          "frame_00012.png",
          "frame_00013.png",
          "frame_00014.png",
          "frame_00015.png",
          "frame_00016.png",
          "frame_00017.png",
          "frame_00018.png",
          "frame_00019.png",
          "frame_00020.png",
          "frame_00021.png",
          "frame_00022.png",
          "frame_00023.png",
          "frame_00024.png",
          "frame_00025.png",
          "frame_00026.png",
          "frame_00027.png",
          "frame_00028.png",
          "frame_00029.png",
          "frame_00030.png",
          "frame_00031.png",
          "frame_00032.png",
          "frame_00033.png",
          "frame_00034.png",
          "frame_00035.png",
          "frame_00036.png",
          "frame_00037.png",
          "frame_00038.png",
          "frame_00039.png",
          "frame_00040.png",
          "frame_00041.png",
          "frame_00042.png",
          "frame_00043.png",
          "frame_00044.png",
          "frame_00045.png",
          "frame_00046.png",
          "frame_00047.png",
          "frame_00048.png",
          "frame_00049.png",
          "frame_00050.png"
        ],
        "normal": [
          "frame_00001.png",
          "frame_00002.png",
          "frame_00003.png",
          "frame_00004.png",
          "frame_00005.png",
          "frame_00006.png",
          "frame_00007.png",
          "frame_00008.png",
          "frame_00009.png",
          "frame_00010.png",
          "frame_00011.png",
          "frame_00012.png",
          "frame_00013.png",
          "frame_00014.png",
          "frame_00015.png",
          "frame_00016.png",
          "frame_00017.png",
          "frame_00018.png",
          "frame_00019.png",
          "frame_00020.png",
          "frame_00021.png",
          "frame_00022.png",
          "frame_00023.png",
          "frame_00024.png",
          "frame_00025.png",
          "frame_00026.png",
          "frame_00027.png",
          "frame_00028.png",
          "frame_00029.png",
          "frame_00030.png",
          "frame_00031.png",
          "frame_00032.png",
          "frame_00033.png",
          "frame_00034.png",
          "frame_00035.png",
          "frame_00036.png",
          "frame_00037.png",
          "frame_00038.png",
          "frame_00039.png",
          "frame_00040.png",
          "frame_00041.png",
          "frame_00042.png",
          "frame_00043.png",
          "frame_00044.png",
          "frame_00045.png",
          "frame_00046.png",
          "frame_00047.png",
          "frame_00048.png",
          "frame_00049.png",
          "frame_00050.png"
        ],
        "mask": [
          "frame_00001.png",
          "frame_00002.png",
          "frame_00003.png",
          "frame_00004.png",
          "frame_00005.png",
          "frame_00006.png",
          "frame_00007.png",
          "frame_00008.png",
          "frame_00009.png",
          "frame_00010.png",
          "frame_00011.png",
          "frame_00012.png",
          "frame_00013.png",
          "frame_00014.png",
          "frame_00015.png",
          "frame_00016.png",
          "frame_00017.png",
          "frame_00018.png",
          "frame_00019.png",
          "frame_00020.png",
          "frame_00021.png",
          "frame_00022.png",
          "frame_00023.png",
          "frame_00024.png",
          "frame_00025.png",
          "frame_00026.png",
          "frame_00027.png",
          "frame_00028.png",
          "frame_00029.png",
          "frame_00030.png",
          "frame_00031.png",
          "frame_00032.png",
          "frame_00033.png",
          "frame_00034.png",
          "frame_00035.png",
          "frame_00036.png",
          "frame_00037.png",
          "frame_00038.png",
          "frame_00039.png",
          "frame_00040.png",
          "frame_00041.png",
          "frame_00042.png",
          "frame_00043.png",
          "frame_00044.png",
          "frame_00045.png",
          "frame_00046.png",
          "frame_00047.png",
          "frame_00048.png",
          "frame_00049.png",
          "frame_00050.png"
        ]
      },
      "frameCount": 50,
      "metadata": {
        "hasGlass": true,
        "isGenerated": true,
        "transparent": false
      }
    },
    {
      "id": "1_snowy_field_smoothGold",
      "name": "Snowy Field SmoothGold",
      "category": "art",
      "categoryFolder": "Roman_Statue",
      "material": "smoothGold",
      "model": "Roman_Statue.blend_Zenobia in Chains statue",
      "environment": "snowy_field_4k.exr",
      "preview": "/instances/Roman_Statue/1_snowy_field_smoothGold/train/frame_00011.png",
      "images": {
        "rgb": [
          "frame_00001.png",
          "frame_00002.png",
          "frame_00003.png",
          "frame_00004.png",
          "frame_00005.png",
          "frame_00006.png",
          "frame_00007.png",
          "frame_00008.png",
          "frame_00009.png",
          "frame_00010.png",
          "frame_00011.png",
          "frame_00012.png",
          "frame_00013.png",
          "frame_00014.png",
          "frame_00015.png",
          "frame_00016.png",
          "frame_00017.png",
          "frame_00018.png",
          "frame_00019.png",
          "frame_00020.png",
          "frame_00021.png",
          "frame_00022.png",
          "frame_00023.png",
          "frame_00024.png",
          "frame_00025.png",
          "frame_00026.png",
          "frame_00027.png",
          "frame_00028.png",
          "frame_00029.png",
          "frame_00030.png",
          "frame_00031.png",
          "frame_00032.png",
          "frame_00033.png",
          "frame_00034.png",
          "frame_00035.png",
          "frame_00036.png",
          "frame_00037.png",
          "frame_00038.png",
          "frame_00039.png",
          "frame_00040.png",
          "frame_00041.png",
          "frame_00042.png",
          "frame_00043.png",
          "frame_00044.png",
          "frame_00045.png",
          "frame_00046.png",
          "frame_00047.png",
          "frame_00048.png",
          "frame_00049.png",
          "frame_00050.png"
        ],
        "depth": [
          "frame_00001.png",
          "frame_00002.png",
          "frame_00003.png",
          "frame_00004.png",
          "frame_00005.png",
          "frame_00006.png",
          "frame_00007.png",
          "frame_00008.png",
          "frame_00009.png",
          "frame_00010.png",
          "frame_00011.png",
          "frame_00012.png",
          "frame_00013.png",
          "frame_00014.png",
          "frame_00015.png",
          "frame_00016.png",
          "frame_00017.png",
          "frame_00018.png",
          "frame_00019.png",
          "frame_00020.png",
          "frame_00021.png",
          "frame_00022.png",
          "frame_00023.png",
          "frame_00024.png",
          "frame_00025.png",
          "frame_00026.png",
          "frame_00027.png",
          "frame_00028.png",
          "frame_00029.png",
          "frame_00030.png",
          "frame_00031.png",
          "frame_00032.png",
          "frame_00033.png",
          "frame_00034.png",
          "frame_00035.png",
          "frame_00036.png",
          "frame_00037.png",
          "frame_00038.png",
          "frame_00039.png",
          "frame_00040.png",
          "frame_00041.png",
          "frame_00042.png",
          "frame_00043.png",
          "frame_00044.png",
          "frame_00045.png",
          "frame_00046.png",
          "frame_00047.png",
          "frame_00048.png",
          "frame_00049.png",
          "frame_00050.png"
        ],
        "normal": [
          "frame_00001.png",
          "frame_00002.png",
          "frame_00003.png",
          "frame_00004.png",
          "frame_00005.png",
          "frame_00006.png",
          "frame_00007.png",
          "frame_00008.png",
          "frame_00009.png",
          "frame_00010.png",
          "frame_00011.png",
          "frame_00012.png",
          "frame_00013.png",
          "frame_00014.png",
          "frame_00015.png",
          "frame_00016.png",
          "frame_00017.png",
          "frame_00018.png",
          "frame_00019.png",
          "frame_00020.png",
          "frame_00021.png",
          "frame_00022.png",
          "frame_00023.png",
          "frame_00024.png",
          "frame_00025.png",
          "frame_00026.png",
          "frame_00027.png",
          "frame_00028.png",
          "frame_00029.png",
          "frame_00030.png",
          "frame_00031.png",
          "frame_00032.png",
          "frame_00033.png",
          "frame_00034.png",
          "frame_00035.png",
          "frame_00036.png",
          "frame_00037.png",
          "frame_00038.png",
          "frame_00039.png",
          "frame_00040.png",
          "frame_00041.png",
          "frame_00042.png",
          "frame_00043.png",
          "frame_00044.png",
          "frame_00045.png",
          "frame_00046.png",
          "frame_00047.png",
          "frame_00048.png",
          "frame_00049.png",
          "frame_00050.png"
        ],
        "mask": [
          "frame_00001.png",
          "frame_00002.png",
          "frame_00003.png",
          "frame_00004.png",
          "frame_00005.png",
          "frame_00006.png",
          "frame_00007.png",
          "frame_00008.png",
          "frame_00009.png",
          "frame_00010.png",
          "frame_00011.png",
          "frame_00012.png",
          "frame_00013.png",
          "frame_00014.png",
          "frame_00015.png",
          "frame_00016.png",
          "frame_00017.png",
          "frame_00018.png",
          "frame_00019.png",
          "frame_00020.png",
          "frame_00021.png",
          "frame_00022.png",
          "frame_00023.png",
          "frame_00024.png",
          "frame_00025.png",
          "frame_00026.png",
          "frame_00027.png",
          "frame_00028.png",
          "frame_00029.png",
          "frame_00030.png",
          "frame_00031.png",
          "frame_00032.png",
          "frame_00033.png",
          "frame_00034.png",
          "frame_00035.png",
          "frame_00036.png",
          "frame_00037.png",
          "frame_00038.png",
          "frame_00039.png",
          "frame_00040.png",
          "frame_00041.png",
          "frame_00042.png",
          "frame_00043.png",
          "frame_00044.png",
          "frame_00045.png",
          "frame_00046.png",
          "frame_00047.png",
          "frame_00048.png",
          "frame_00049.png",
          "frame_00050.png"
        ]
      },
      "frameCount": 50,
      "metadata": {
        "hasGlass": false,
        "isGenerated": false,
        "transparent": false
      }
    },
    {
      "id": "2_snowy_field_smoothGold",
      "name": "Snowy Field SmoothGold",
      "category": "art",
      "categoryFolder": "Roman_Statue",
      "material": "smoothGold",
      "model": "Roman_Statue.blend_Venus_Kissing_Cupid",
      "environment": "snowy_field_4k.exr",
      "preview": "/instances/Roman_Statue/2_snowy_field_smoothGold/train/frame_00011.png",
      "images": {
        "rgb": [
          "frame_00001.png",
          "frame_00002.png",
          "frame_00003.png",
          "frame_00004.png",
          "frame_00005.png",
          "frame_00006.png",
          "frame_00007.png",
          "frame_00008.png",
          "frame_00009.png",
          "frame_00010.png",
          "frame_00011.png",
          "frame_00012.png",
          "frame_00013.png",
          "frame_00014.png",
          "frame_00015.png",
          "frame_00016.png",
          "frame_00017.png",
          "frame_00018.png",
          "frame_00019.png",
          "frame_00020.png",
          "frame_00021.png",
          "frame_00022.png",
          "frame_00023.png",
          "frame_00024.png",
          "frame_00025.png",
          "frame_00026.png",
          "frame_00027.png",
          "frame_00028.png",
          "frame_00029.png",
          "frame_00030.png",
          "frame_00031.png",
          "frame_00032.png",
          "frame_00033.png",
          "frame_00034.png",
          "frame_00035.png",
          "frame_00036.png",
          "frame_00037.png",
          "frame_00038.png",
          "frame_00039.png",
          "frame_00040.png",
          "frame_00041.png",
          "frame_00042.png",
          "frame_00043.png",
          "frame_00044.png",
          "frame_00045.png",
          "frame_00046.png",
          "frame_00047.png",
          "frame_00048.png",
          "frame_00049.png",
          "frame_00050.png"
        ],
        "depth": [
          "frame_00001.png",
          "frame_00002.png",
          "frame_00003.png",
          "frame_00004.png",
          "frame_00005.png",
          "frame_00006.png",
          "frame_00007.png",
          "frame_00008.png",
          "frame_00009.png",
          "frame_00010.png",
          "frame_00011.png",
          "frame_00012.png",
          "frame_00013.png",
          "frame_00014.png",
          "frame_00015.png",
          "frame_00016.png",
          "frame_00017.png",
          "frame_00018.png",
          "frame_00019.png",
          "frame_00020.png",
          "frame_00021.png",
          "frame_00022.png",
          "frame_00023.png",
          "frame_00024.png",
          "frame_00025.png",
          "frame_00026.png",
          "frame_00027.png",
          "frame_00028.png",
          "frame_00029.png",
          "frame_00030.png",
          "frame_00031.png",
          "frame_00032.png",
          "frame_00033.png",
          "frame_00034.png",
          "frame_00035.png",
          "frame_00036.png",
          "frame_00037.png",
          "frame_00038.png",
          "frame_00039.png",
          "frame_00040.png",
          "frame_00041.png",
          "frame_00042.png",
          "frame_00043.png",
          "frame_00044.png",
          "frame_00045.png",
          "frame_00046.png",
          "frame_00047.png",
          "frame_00048.png",
          "frame_00049.png",
          "frame_00050.png"
        ],
        "normal": [
          "frame_00001.png",
          "frame_00002.png",
          "frame_00003.png",
          "frame_00004.png",
          "frame_00005.png",
          "frame_00006.png",
          "frame_00007.png",
          "frame_00008.png",
          "frame_00009.png",
          "frame_00010.png",
          "frame_00011.png",
          "frame_00012.png",
          "frame_00013.png",
          "frame_00014.png",
          "frame_00015.png",
          "frame_00016.png",
          "frame_00017.png",
          "frame_00018.png",
          "frame_00019.png",
          "frame_00020.png",
          "frame_00021.png",
          "frame_00022.png",
          "frame_00023.png",
          "frame_00024.png",
          "frame_00025.png",
          "frame_00026.png",
          "frame_00027.png",
          "frame_00028.png",
          "frame_00029.png",
          "frame_00030.png",
          "frame_00031.png",
          "frame_00032.png",
          "frame_00033.png",
          "frame_00034.png",
          "frame_00035.png",
          "frame_00036.png",
          "frame_00037.png",
          "frame_00038.png",
          "frame_00039.png",
          "frame_00040.png",
          "frame_00041.png",
          "frame_00042.png",
          "frame_00043.png",
          "frame_00044.png",
          "frame_00045.png",
          "frame_00046.png",
          "frame_00047.png",
          "frame_00048.png",
          "frame_00049.png",
          "frame_00050.png"
        ],
        "mask": [
          "frame_00001.png",
          "frame_00002.png",
          "frame_00003.png",
          "frame_00004.png",
          "frame_00005.png",
          "frame_00006.png",
          "frame_00007.png",
          "frame_00008.png",
          "frame_00009.png",
          "frame_00010.png",
          "frame_00011.png",
          "frame_00012.png",
          "frame_00013.png",
          "frame_00014.png",
          "frame_00015.png",
          "frame_00016.png",
          "frame_00017.png",
          "frame_00018.png",
          "frame_00019.png",
          "frame_00020.png",
          "frame_00021.png",
          "frame_00022.png",
          "frame_00023.png",
          "frame_00024.png",
          "frame_00025.png",
          "frame_00026.png",
          "frame_00027.png",
          "frame_00028.png",
          "frame_00029.png",
          "frame_00030.png",
          "frame_00031.png",
          "frame_00032.png",
          "frame_00033.png",
          "frame_00034.png",
          "frame_00035.png",
          "frame_00036.png",
          "frame_00037.png",
          "frame_00038.png",
          "frame_00039.png",
          "frame_00040.png",
          "frame_00041.png",
          "frame_00042.png",
          "frame_00043.png",
          "frame_00044.png",
          "frame_00045.png",
          "frame_00046.png",
          "frame_00047.png",
          "frame_00048.png",
          "frame_00049.png",
          "frame_00050.png"
        ]
      },
      "frameCount": 50,
      "metadata": {
        "hasGlass": false,
        "isGenerated": false,
        "transparent": false
      }
    },
    {
      "id": "3_snowy_field_smoothGold",
      "name": "Snowy Field SmoothGold",
      "category": "art",
      "categoryFolder": "Roman_Statue",
      "material": "smoothGold",
      "model": "Roman_Statue.blend_Venus statue in Vienna",
      "environment": "snowy_field_4k.exr",
      "preview": "/instances/Roman_Statue/3_snowy_field_smoothGold/train/frame_00011.png",
      "images": {
        "rgb": [
          "frame_00001.png",
          "frame_00002.png",
          "frame_00003.png",
          "frame_00004.png",
          "frame_00005.png",
          "frame_00006.png",
          "frame_00007.png",
          "frame_00008.png",
          "frame_00009.png",
          "frame_00010.png",
          "frame_00011.png",
          "frame_00012.png",
          "frame_00013.png",
          "frame_00014.png",
          "frame_00015.png",
          "frame_00016.png",
          "frame_00017.png",
          "frame_00018.png",
          "frame_00019.png",
          "frame_00020.png",
          "frame_00021.png",
          "frame_00022.png",
          "frame_00023.png",
          "frame_00024.png",
          "frame_00025.png",
          "frame_00026.png",
          "frame_00027.png",
          "frame_00028.png",
          "frame_00029.png",
          "frame_00030.png",
          "frame_00031.png",
          "frame_00032.png",
          "frame_00033.png",
          "frame_00034.png",
          "frame_00035.png",
          "frame_00036.png",
          "frame_00037.png",
          "frame_00038.png",
          "frame_00039.png",
          "frame_00040.png",
          "frame_00041.png",
          "frame_00042.png",
          "frame_00043.png",
          "frame_00044.png",
          "frame_00045.png",
          "frame_00046.png",
          "frame_00047.png",
          "frame_00048.png",
          "frame_00049.png",
          "frame_00050.png"
        ],
        "depth": [
          "frame_00001.png",
          "frame_00002.png",
          "frame_00003.png",
          "frame_00004.png",
          "frame_00005.png",
          "frame_00006.png",
          "frame_00007.png",
          "frame_00008.png",
          "frame_00009.png",
          "frame_00010.png",
          "frame_00011.png",
          "frame_00012.png",
          "frame_00013.png",
          "frame_00014.png",
          "frame_00015.png",
          "frame_00016.png",
          "frame_00017.png",
          "frame_00018.png",
          "frame_00019.png",
          "frame_00020.png",
          "frame_00021.png",
          "frame_00022.png",
          "frame_00023.png",
          "frame_00024.png",
          "frame_00025.png",
          "frame_00026.png",
          "frame_00027.png",
          "frame_00028.png",
          "frame_00029.png",
          "frame_00030.png",
          "frame_00031.png",
          "frame_00032.png",
          "frame_00033.png",
          "frame_00034.png",
          "frame_00035.png",
          "frame_00036.png",
          "frame_00037.png",
          "frame_00038.png",
          "frame_00039.png",
          "frame_00040.png",
          "frame_00041.png",
          "frame_00042.png",
          "frame_00043.png",
          "frame_00044.png",
          "frame_00045.png",
          "frame_00046.png",
          "frame_00047.png",
          "frame_00048.png",
          "frame_00049.png",
          "frame_00050.png"
        ],
        "normal": [
          "frame_00001.png",
          "frame_00002.png",
          "frame_00003.png",
          "frame_00004.png",
          "frame_00005.png",
          "frame_00006.png",
          "frame_00007.png",
          "frame_00008.png",
          "frame_00009.png",
          "frame_00010.png",
          "frame_00011.png",
          "frame_00012.png",
          "frame_00013.png",
          "frame_00014.png",
          "frame_00015.png",
          "frame_00016.png",
          "frame_00017.png",
          "frame_00018.png",
          "frame_00019.png",
          "frame_00020.png",
          "frame_00021.png",
          "frame_00022.png",
          "frame_00023.png",
          "frame_00024.png",
          "frame_00025.png",
          "frame_00026.png",
          "frame_00027.png",
          "frame_00028.png",
          "frame_00029.png",
          "frame_00030.png",
          "frame_00031.png",
          "frame_00032.png",
          "frame_00033.png",
          "frame_00034.png",
          "frame_00035.png",
          "frame_00036.png",
          "frame_00037.png",
          "frame_00038.png",
          "frame_00039.png",
          "frame_00040.png",
          "frame_00041.png",
          "frame_00042.png",
          "frame_00043.png",
          "frame_00044.png",
          "frame_00045.png",
          "frame_00046.png",
          "frame_00047.png",
          "frame_00048.png",
          "frame_00049.png",
          "frame_00050.png"
        ],
        "mask": [
          "frame_00001.png",
          "frame_00002.png",
          "frame_00003.png",
          "frame_00004.png",
          "frame_00005.png",
          "frame_00006.png",
          "frame_00007.png",
          "frame_00008.png",
          "frame_00009.png",
          "frame_00010.png",
          "frame_00011.png",
          "frame_00012.png",
          "frame_00013.png",
          "frame_00014.png",
          "frame_00015.png",
          "frame_00016.png",
          "frame_00017.png",
          "frame_00018.png",
          "frame_00019.png",
          "frame_00020.png",
          "frame_00021.png",
          "frame_00022.png",
          "frame_00023.png",
          "frame_00024.png",
          "frame_00025.png",
          "frame_00026.png",
          "frame_00027.png",
          "frame_00028.png",
          "frame_00029.png",
          "frame_00030.png",
          "frame_00031.png",
          "frame_00032.png",
          "frame_00033.png",
          "frame_00034.png",
          "frame_00035.png",
          "frame_00036.png",
          "frame_00037.png",
          "frame_00038.png",
          "frame_00039.png",
          "frame_00040.png",
          "frame_00041.png",
          "frame_00042.png",
          "frame_00043.png",
          "frame_00044.png",
          "frame_00045.png",
          "frame_00046.png",
          "frame_00047.png",
          "frame_00048.png",
          "frame_00049.png",
          "frame_00050.png"
        ]
      },
      "frameCount": 50,
      "metadata": {
        "hasGlass": false,
        "isGenerated": false,
        "transparent": false
      }
    },
    {
      "id": "1_snowy_field_smoothGold_glass",
      "name": "Snowy Field SmoothGold Glass",
      "category": "art",
      "categoryFolder": "Roman_Statue_glass",
      "material": "smoothGold",
      "model": "Roman_Statue.blend_Zenobia in Chains statue",
      "environment": "snowy_field_4k.exr",
      "preview": "/instances/Roman_Statue_glass/1_snowy_field_smoothGold_glass/train/frame_00011.png",
      "images": {
        "rgb": [
          "frame_00001.png",
          "frame_00002.png",
          "frame_00003.png",
          "frame_00004.png",
          "frame_00005.png",
          "frame_00006.png",
          "frame_00007.png",
          "frame_00008.png",
          "frame_00009.png",
          "frame_00010.png",
          "frame_00011.png",
          "frame_00012.png",
          "frame_00013.png",
          "frame_00014.png",
          "frame_00015.png",
          "frame_00016.png",
          "frame_00017.png",
          "frame_00018.png",
          "frame_00019.png",
          "frame_00020.png",
          "frame_00021.png",
          "frame_00022.png",
          "frame_00023.png",
          "frame_00024.png",
          "frame_00025.png",
          "frame_00026.png",
          "frame_00027.png",
          "frame_00028.png",
          "frame_00029.png",
          "frame_00030.png",
          "frame_00031.png",
          "frame_00032.png",
          "frame_00033.png",
          "frame_00034.png",
          "frame_00035.png",
          "frame_00036.png",
          "frame_00037.png",
          "frame_00038.png",
          "frame_00039.png",
          "frame_00040.png",
          "frame_00041.png",
          "frame_00042.png",
          "frame_00043.png",
          "frame_00044.png",
          "frame_00045.png",
          "frame_00046.png",
          "frame_00047.png",
          "frame_00048.png",
          "frame_00049.png",
          "frame_00050.png"
        ],
        "depth": [
          "frame_00001.png",
          "frame_00002.png",
          "frame_00003.png",
          "frame_00004.png",
          "frame_00005.png",
          "frame_00006.png",
          "frame_00007.png",
          "frame_00008.png",
          "frame_00009.png",
          "frame_00010.png",
          "frame_00011.png",
          "frame_00012.png",
          "frame_00013.png",
          "frame_00014.png",
          "frame_00015.png",
          "frame_00016.png",
          "frame_00017.png",
          "frame_00018.png",
          "frame_00019.png",
          "frame_00020.png",
          "frame_00021.png",
          "frame_00022.png",
          "frame_00023.png",
          "frame_00024.png",
          "frame_00025.png",
          "frame_00026.png",
          "frame_00027.png",
          "frame_00028.png",
          "frame_00029.png",
          "frame_00030.png",
          "frame_00031.png",
          "frame_00032.png",
          "frame_00033.png",
          "frame_00034.png",
          "frame_00035.png",
          "frame_00036.png",
          "frame_00037.png",
          "frame_00038.png",
          "frame_00039.png",
          "frame_00040.png",
          "frame_00041.png",
          "frame_00042.png",
          "frame_00043.png",
          "frame_00044.png",
          "frame_00045.png",
          "frame_00046.png",
          "frame_00047.png",
          "frame_00048.png",
          "frame_00049.png",
          "frame_00050.png"
        ],
        "normal": [
          "frame_00001.png",
          "frame_00002.png",
          "frame_00003.png",
          "frame_00004.png",
          "frame_00005.png",
          "frame_00006.png",
          "frame_00007.png",
          "frame_00008.png",
          "frame_00009.png",
          "frame_00010.png",
          "frame_00011.png",
          "frame_00012.png",
          "frame_00013.png",
          "frame_00014.png",
          "frame_00015.png",
          "frame_00016.png",
          "frame_00017.png",
          "frame_00018.png",
          "frame_00019.png",
          "frame_00020.png",
          "frame_00021.png",
          "frame_00022.png",
          "frame_00023.png",
          "frame_00024.png",
          "frame_00025.png",
          "frame_00026.png",
          "frame_00027.png",
          "frame_00028.png",
          "frame_00029.png",
          "frame_00030.png",
          "frame_00031.png",
          "frame_00032.png",
          "frame_00033.png",
          "frame_00034.png",
          "frame_00035.png",
          "frame_00036.png",
          "frame_00037.png",
          "frame_00038.png",
          "frame_00039.png",
          "frame_00040.png",
          "frame_00041.png",
          "frame_00042.png",
          "frame_00043.png",
          "frame_00044.png",
          "frame_00045.png",
          "frame_00046.png",
          "frame_00047.png",
          "frame_00048.png",
          "frame_00049.png",
          "frame_00050.png"
        ],
        "mask": [
          "frame_00001.png",
          "frame_00002.png",
          "frame_00003.png",
          "frame_00004.png",
          "frame_00005.png",
          "frame_00006.png",
          "frame_00007.png",
          "frame_00008.png",
          "frame_00009.png",
          "frame_00010.png",
          "frame_00011.png",
          "frame_00012.png",
          "frame_00013.png",
          "frame_00014.png",
          "frame_00015.png",
          "frame_00016.png",
          "frame_00017.png",
          "frame_00018.png",
          "frame_00019.png",
          "frame_00020.png",
          "frame_00021.png",
          "frame_00022.png",
          "frame_00023.png",
          "frame_00024.png",
          "frame_00025.png",
          "frame_00026.png",
          "frame_00027.png",
          "frame_00028.png",
          "frame_00029.png",
          "frame_00030.png",
          "frame_00031.png",
          "frame_00032.png",
          "frame_00033.png",
          "frame_00034.png",
          "frame_00035.png",
          "frame_00036.png",
          "frame_00037.png",
          "frame_00038.png",
          "frame_00039.png",
          "frame_00040.png",
          "frame_00041.png",
          "frame_00042.png",
          "frame_00043.png",
          "frame_00044.png",
          "frame_00045.png",
          "frame_00046.png",
          "frame_00047.png",
          "frame_00048.png",
          "frame_00049.png",
          "frame_00050.png"
        ]
      },
      "frameCount": 50,
      "metadata": {
        "hasGlass": true,
        "isGenerated": false,
        "transparent": false
      }
    },
    {
      "id": "2_snowy_field_smoothGold_glass",
      "name": "Snowy Field SmoothGold Glass",
      "category": "art",
      "categoryFolder": "Roman_Statue_glass",
      "material": "smoothGold",
      "model": "Roman_Statue.blend_Venus_Kissing_Cupid",
      "environment": "snowy_field_4k.exr",
      "preview": "/instances/Roman_Statue_glass/2_snowy_field_smoothGold_glass/train/frame_00011.png",
      "images": {
        "rgb": [
          "frame_00001.png",
          "frame_00002.png",
          "frame_00003.png",
          "frame_00004.png",
          "frame_00005.png",
          "frame_00006.png",
          "frame_00007.png",
          "frame_00008.png",
          "frame_00009.png",
          "frame_00010.png",
          "frame_00011.png",
          "frame_00012.png",
          "frame_00013.png",
          "frame_00014.png",
          "frame_00015.png",
          "frame_00016.png",
          "frame_00017.png",
          "frame_00018.png",
          "frame_00019.png",
          "frame_00020.png",
          "frame_00021.png",
          "frame_00022.png",
          "frame_00023.png",
          "frame_00024.png",
          "frame_00025.png",
          "frame_00026.png",
          "frame_00027.png",
          "frame_00028.png",
          "frame_00029.png",
          "frame_00030.png",
          "frame_00031.png",
          "frame_00032.png",
          "frame_00033.png",
          "frame_00034.png",
          "frame_00035.png",
          "frame_00036.png",
          "frame_00037.png",
          "frame_00038.png",
          "frame_00039.png",
          "frame_00040.png",
          "frame_00041.png",
          "frame_00042.png",
          "frame_00043.png",
          "frame_00044.png",
          "frame_00045.png",
          "frame_00046.png",
          "frame_00047.png",
          "frame_00048.png",
          "frame_00049.png",
          "frame_00050.png"
        ],
        "depth": [
          "frame_00001.png",
          "frame_00002.png",
          "frame_00003.png",
          "frame_00004.png",
          "frame_00005.png",
          "frame_00006.png",
          "frame_00007.png",
          "frame_00008.png",
          "frame_00009.png",
          "frame_00010.png",
          "frame_00011.png",
          "frame_00012.png",
          "frame_00013.png",
          "frame_00014.png",
          "frame_00015.png",
          "frame_00016.png",
          "frame_00017.png",
          "frame_00018.png",
          "frame_00019.png",
          "frame_00020.png",
          "frame_00021.png",
          "frame_00022.png",
          "frame_00023.png",
          "frame_00024.png",
          "frame_00025.png",
          "frame_00026.png",
          "frame_00027.png",
          "frame_00028.png",
          "frame_00029.png",
          "frame_00030.png",
          "frame_00031.png",
          "frame_00032.png",
          "frame_00033.png",
          "frame_00034.png",
          "frame_00035.png",
          "frame_00036.png",
          "frame_00037.png",
          "frame_00038.png",
          "frame_00039.png",
          "frame_00040.png",
          "frame_00041.png",
          "frame_00042.png",
          "frame_00043.png",
          "frame_00044.png",
          "frame_00045.png",
          "frame_00046.png",
          "frame_00047.png",
          "frame_00048.png",
          "frame_00049.png",
          "frame_00050.png"
        ],
        "normal": [
          "frame_00001.png",
          "frame_00002.png",
          "frame_00003.png",
          "frame_00004.png",
          "frame_00005.png",
          "frame_00006.png",
          "frame_00007.png",
          "frame_00008.png",
          "frame_00009.png",
          "frame_00010.png",
          "frame_00011.png",
          "frame_00012.png",
          "frame_00013.png",
          "frame_00014.png",
          "frame_00015.png",
          "frame_00016.png",
          "frame_00017.png",
          "frame_00018.png",
          "frame_00019.png",
          "frame_00020.png",
          "frame_00021.png",
          "frame_00022.png",
          "frame_00023.png",
          "frame_00024.png",
          "frame_00025.png",
          "frame_00026.png",
          "frame_00027.png",
          "frame_00028.png",
          "frame_00029.png",
          "frame_00030.png",
          "frame_00031.png",
          "frame_00032.png",
          "frame_00033.png",
          "frame_00034.png",
          "frame_00035.png",
          "frame_00036.png",
          "frame_00037.png",
          "frame_00038.png",
          "frame_00039.png",
          "frame_00040.png",
          "frame_00041.png",
          "frame_00042.png",
          "frame_00043.png",
          "frame_00044.png",
          "frame_00045.png",
          "frame_00046.png",
          "frame_00047.png",
          "frame_00048.png",
          "frame_00049.png",
          "frame_00050.png"
        ],
        "mask": [
          "frame_00001.png",
          "frame_00002.png",
          "frame_00003.png",
          "frame_00004.png",
          "frame_00005.png",
          "frame_00006.png",
          "frame_00007.png",
          "frame_00008.png",
          "frame_00009.png",
          "frame_00010.png",
          "frame_00011.png",
          "frame_00012.png",
          "frame_00013.png",
          "frame_00014.png",
          "frame_00015.png",
          "frame_00016.png",
          "frame_00017.png",
          "frame_00018.png",
          "frame_00019.png",
          "frame_00020.png",
          "frame_00021.png",
          "frame_00022.png",
          "frame_00023.png",
          "frame_00024.png",
          "frame_00025.png",
          "frame_00026.png",
          "frame_00027.png",
          "frame_00028.png",
          "frame_00029.png",
          "frame_00030.png",
          "frame_00031.png",
          "frame_00032.png",
          "frame_00033.png",
          "frame_00034.png",
          "frame_00035.png",
          "frame_00036.png",
          "frame_00037.png",
          "frame_00038.png",
          "frame_00039.png",
          "frame_00040.png",
          "frame_00041.png",
          "frame_00042.png",
          "frame_00043.png",
          "frame_00044.png",
          "frame_00045.png",
          "frame_00046.png",
          "frame_00047.png",
          "frame_00048.png",
          "frame_00049.png",
          "frame_00050.png"
        ]
      },
      "frameCount": 50,
      "metadata": {
        "hasGlass": true,
        "isGenerated": false,
        "transparent": false
      }
    },
    {
      "id": "3_snowy_field_smoothGold_glass",
      "name": "Snowy Field SmoothGold Glass",
      "category": "art",
      "categoryFolder": "Roman_Statue_glass",
      "material": "smoothGold",
      "model": "Roman_Statue.blend_Venus statue in Vienna",
      "environment": "snowy_field_4k.exr",
      "preview": "/instances/Roman_Statue_glass/3_snowy_field_smoothGold_glass/train/frame_00011.png",
      "images": {
        "rgb": [
          "frame_00001.png",
          "frame_00002.png",
          "frame_00003.png",
          "frame_00004.png",
          "frame_00005.png",
          "frame_00006.png",
          "frame_00007.png",
          "frame_00008.png",
          "frame_00009.png",
          "frame_00010.png",
          "frame_00011.png",
          "frame_00012.png",
          "frame_00013.png",
          "frame_00014.png",
          "frame_00015.png",
          "frame_00016.png",
          "frame_00017.png",
          "frame_00018.png",
          "frame_00019.png",
          "frame_00020.png",
          "frame_00021.png",
          "frame_00022.png",
          "frame_00023.png",
          "frame_00024.png",
          "frame_00025.png",
          "frame_00026.png",
          "frame_00027.png",
          "frame_00028.png",
          "frame_00029.png",
          "frame_00030.png",
          "frame_00031.png",
          "frame_00032.png",
          "frame_00033.png",
          "frame_00034.png",
          "frame_00035.png",
          "frame_00036.png",
          "frame_00037.png",
          "frame_00038.png",
          "frame_00039.png",
          "frame_00040.png",
          "frame_00041.png",
          "frame_00042.png",
          "frame_00043.png",
          "frame_00044.png",
          "frame_00045.png",
          "frame_00046.png",
          "frame_00047.png",
          "frame_00048.png",
          "frame_00049.png",
          "frame_00050.png"
        ],
        "depth": [
          "frame_00001.png",
          "frame_00002.png",
          "frame_00003.png",
          "frame_00004.png",
          "frame_00005.png",
          "frame_00006.png",
          "frame_00007.png",
          "frame_00008.png",
          "frame_00009.png",
          "frame_00010.png",
          "frame_00011.png",
          "frame_00012.png",
          "frame_00013.png",
          "frame_00014.png",
          "frame_00015.png",
          "frame_00016.png",
          "frame_00017.png",
          "frame_00018.png",
          "frame_00019.png",
          "frame_00020.png",
          "frame_00021.png",
          "frame_00022.png",
          "frame_00023.png",
          "frame_00024.png",
          "frame_00025.png",
          "frame_00026.png",
          "frame_00027.png",
          "frame_00028.png",
          "frame_00029.png",
          "frame_00030.png",
          "frame_00031.png",
          "frame_00032.png",
          "frame_00033.png",
          "frame_00034.png",
          "frame_00035.png",
          "frame_00036.png",
          "frame_00037.png",
          "frame_00038.png",
          "frame_00039.png",
          "frame_00040.png",
          "frame_00041.png",
          "frame_00042.png",
          "frame_00043.png",
          "frame_00044.png",
          "frame_00045.png",
          "frame_00046.png",
          "frame_00047.png",
          "frame_00048.png",
          "frame_00049.png",
          "frame_00050.png"
        ],
        "normal": [
          "frame_00001.png",
          "frame_00002.png",
          "frame_00003.png",
          "frame_00004.png",
          "frame_00005.png",
          "frame_00006.png",
          "frame_00007.png",
          "frame_00008.png",
          "frame_00009.png",
          "frame_00010.png",
          "frame_00011.png",
          "frame_00012.png",
          "frame_00013.png",
          "frame_00014.png",
          "frame_00015.png",
          "frame_00016.png",
          "frame_00017.png",
          "frame_00018.png",
          "frame_00019.png",
          "frame_00020.png",
          "frame_00021.png",
          "frame_00022.png",
          "frame_00023.png",
          "frame_00024.png",
          "frame_00025.png",
          "frame_00026.png",
          "frame_00027.png",
          "frame_00028.png",
          "frame_00029.png",
          "frame_00030.png",
          "frame_00031.png",
          "frame_00032.png",
          "frame_00033.png",
          "frame_00034.png",
          "frame_00035.png",
          "frame_00036.png",
          "frame_00037.png",
          "frame_00038.png",
          "frame_00039.png",
          "frame_00040.png",
          "frame_00041.png",
          "frame_00042.png",
          "frame_00043.png",
          "frame_00044.png",
          "frame_00045.png",
          "frame_00046.png",
          "frame_00047.png",
          "frame_00048.png",
          "frame_00049.png",
          "frame_00050.png"
        ],
        "mask": [
          "frame_00001.png",
          "frame_00002.png",
          "frame_00003.png",
          "frame_00004.png",
          "frame_00005.png",
          "frame_00006.png",
          "frame_00007.png",
          "frame_00008.png",
          "frame_00009.png",
          "frame_00010.png",
          "frame_00011.png",
          "frame_00012.png",
          "frame_00013.png",
          "frame_00014.png",
          "frame_00015.png",
          "frame_00016.png",
          "frame_00017.png",
          "frame_00018.png",
          "frame_00019.png",
          "frame_00020.png",
          "frame_00021.png",
          "frame_00022.png",
          "frame_00023.png",
          "frame_00024.png",
          "frame_00025.png",
          "frame_00026.png",
          "frame_00027.png",
          "frame_00028.png",
          "frame_00029.png",
          "frame_00030.png",
          "frame_00031.png",
          "frame_00032.png",
          "frame_00033.png",
          "frame_00034.png",
          "frame_00035.png",
          "frame_00036.png",
          "frame_00037.png",
          "frame_00038.png",
          "frame_00039.png",
          "frame_00040.png",
          "frame_00041.png",
          "frame_00042.png",
          "frame_00043.png",
          "frame_00044.png",
          "frame_00045.png",
          "frame_00046.png",
          "frame_00047.png",
          "frame_00048.png",
          "frame_00049.png",
          "frame_00050.png"
        ]
      },
      "frameCount": 50,
      "metadata": {
        "hasGlass": true,
        "isGenerated": false,
        "transparent": false
      }
    }
  ],
  "categories": [
    "art"
  ],
  "totalInstances": 12,
  "lastUpdated": "2025-07-30T07:38:06.846Z"
}